LICENSE
MANIFEST.in
README.md
package.json
setup.py
dash_lumino_components/BoxPanel.py
dash_lumino_components/Command.py
dash_lumino_components/DockPanel.py
dash_lumino_components/Menu.py
dash_lumino_components/MenuBar.py
dash_lumino_components/Panel.py
dash_lumino_components/Separator.py
dash_lumino_components/SplitPanel.py
dash_lumino_components/TabPanel.py
dash_lumino_components/Widget.py
dash_lumino_components/__init__.py
dash_lumino_components/_imports_.py
dash_lumino_components/dash_lumino_components.min.js
dash_lumino_components/dash_lumino_components.min.js.map
dash_lumino_components/metadata.json
dash_lumino_components/package-info.json
dash_lumino_components.egg-info/PKG-INFO
dash_lumino_components.egg-info/SOURCES.txt
dash_lumino_components.egg-info/dependency_links.txt
dash_lumino_components.egg-info/requires.txt
dash_lumino_components.egg-info/top_level.txt