Metadata-Version: 2.1
Name: dash-lumino-components
Version: 0.0.15
Summary: Lumino (JupyterLab) components for Plotly Dash
Home-page: https://github.com/VK/dash-lumino-components
Author: Viktor Krückl <viktor@krueckl.de>
License: MIT
Platform: UNKNOWN
Classifier: Framework :: Dash
